LICENSE.txt
MANIFEST.in
README.md
pyproject.toml
setup.cfg
setup.py
src/wmm2020/CMakeLists.txt
src/wmm2020/WMM.COF
src/wmm2020/__init__.py
src/wmm2020/base.py
src/wmm2020/build.py
src/wmm2020/meson.build
src/wmm2020/plots.py
src/wmm2020/setup.cmake
src/wmm2020/test_input.asc
src/wmm2020.egg-info/PKG-INFO
src/wmm2020.egg-info/SOURCES.txt
src/wmm2020.egg-info/dependency_links.txt
src/wmm2020.egg-info/not-zip-safe
src/wmm2020.egg-info/requires.txt
src/wmm2020.egg-info/top_level.txt
src/wmm2020/src/EGM9615.h
src/wmm2020/src/GeomagnetismHeader.h
src/wmm2020/src/GeomagnetismLibrary.c
src/wmm2020/src/wmm_file.c
src/wmm2020/src/wmm_grid.c
src/wmm2020/src/wmm_point.c
src/wmm2020/src/wmm_point_sub.c