Metadata-Version: 2.1
Name: wmm2020
Version: 1.1.1
Summary: WMM2020 geomagnetic model with simple object-oriented Python interface
Home-page: https://github.com/space-physics/wmm2020
Author: Michael Hirsch, Ph.D.
License: UNKNOWN
Keywords: geomagnetic
Platform: UNKNOWN
Classifier: Development Status :: 5 - Production/Stable
Classifier: Environment :: Console
Classifier: Intended Audience :: Science/Research
Classifier: Operating System :: OS Independent
Classifier: Programming Language :: Python :: 3
Classifier: Topic :: Scientific/Engineering
Requires-Python: >=3.7
Provides-Extra: tests
Provides-Extra: lint
